{"label_logits": [3.755409002304077, -0.6334969401359558, -4.178895473480225], "label_probs": [0.987388551235199, 0.012257739901542664, 0.000353723211446777], "claim": "Taylor Swift is an American singer-songwriter.", "premise_source_doc_id": "Taylor_Swift", "premise_source_doc_line_num": 0, "premise_source_doc_sentence": "Taylor Alison Swift  (  born December 13 , 1989  )  is an American singer-songwriter ."}
{"label_logits": [-0.8958242535591125, -4.742842197418213, 3.1049611568450928], "label_probs": [0.01796545274555683, 0.0003834419185295701, 0.9816511273384094], "claim": "Taylor Swift is an American singer-songwriter.", "premise_source_doc_id": "Taylor_Swift", "premise_source_doc_line_num": 1, "premise_source_doc_sentence": "One of the most popular contemporary female recording artists , she is known for narrative songs about her personal life , which has received much media attention ."}
{"label_logits": [0.3049197494983673, -4.182191848754883, 2.328139543533325], "label_probs": [0.11663319170475006, 0.0013124853139743209, 0.882054328918457], "claim": "Taylor Swift is an American singer-songwriter.", "premise_source_doc_id": "Taylor_Swift", "premise_source_doc_line_num": 4, "premise_source_doc_sentence": "Born and raised in Pennsylvania , Swift moved to Nashville , Tennessee at age 14 to pursue a career in country music ."}
{"label_logits": [-2.4411303997039795, -3.8266196250915527, 3.209463357925415], "label_probs": [0.003500046208500862, 0.000875716155860573, 0.9956242442131042], "claim": "Taylor Swift is an American singer-songwriter.", "premise_source_doc_id": "Taylor_Swift", "premise_source_doc_line_num": 5, "premise_source_doc_sentence": "She signed with the independent label Big Machine Records and became the youngest artist ever signed by the Sony/ATV Music publishing house ."}
{"label_logits": [-1.2560967206954956, -2.857933521270752, 2.4943768978118896], "label_probs": [0.02286093309521675, 0.004607073031365871, 0.9725319743156433], "claim": "Taylor Swift is an American singer-songwriter.", "premise_source_doc_id": "Taylor_Swift", "premise_source_doc_line_num": 6, "premise_source_doc_sentence": "Her eponymous debut album in 2006 peaked at number five on Billboard 200 and spent the most weeks on the chart in the 2000s ."}
{"label_logits": [1.2667322158813477, -5.069085597991943, 2.1494123935699463], "label_probs": [0.2924710512161255, 0.0005181697779335082, 0.7070107460021973], "claim": "Taylor Swift is an American singer-songwriter.", "premise_source_doc_id": "Taylor_Swift", "premise_source_doc_line_num": 7, "premise_source_doc_sentence": "The album 's third single , `` Our Song '' , made her the youngest person to single-handedly write and perform a number-one song on the Hot Country Songs chart ."}
{"label_logits": [-1.2104467153549194, -3.3837735652923584, 2.4875173568725586], "label_probs": [0.024108676239848137, 0.0027435284573584795, 0.9731478095054626], "claim": "Taylor Swift is an American singer-songwriter.", "premise_source_doc_id": "Taylor_Swift", "premise_source_doc_line_num": 8, "premise_source_doc_sentence": "Swift 's second album , Fearless , was released in 2008 ."}
{"label_logits": [-0.09264088422060013, -3.3411049842834473, 2.0147974491119385], "label_probs": [0.10792174935340881, 0.004191011190414429, 0.8878872394561768], "claim": "Taylor Swift is an American singer-songwriter.", "premise_source_doc_id": "Taylor_Swift", "premise_source_doc_line_num": 9, "premise_source_doc_sentence": "Buoyed by the pop crossover success of the singles `` Love Story '' and `` You Belong with Me '' , Fearless became the best-selling album of 2009 in the United States ."}
{"label_logits": [-1.0972262620925903, -2.5521748065948486, 1.9719817638397217], "label_probs": [0.04394008219242096, 0.01025616005063057, 0.9458037614822388], "claim": "Taylor Swift is an American singer-songwriter.", "premise_source_doc_id": "Taylor_Swift", "premise_source_doc_line_num": 10, "premise_source_doc_sentence": "The album won four Grammy Awards , with Swift becoming the youngest Album of the Year winner ."}
{"label_logits": [-0.6957885026931763, -2.9116268157958984, 1.9745625257492065], "label_probs": [0.06429173052310944, 0.007011787034571171, 0.9286965131759644], "claim": "Taylor Swift is an American singer-songwriter.", "premise_source_doc_id": "Taylor_Swift", "premise_source_doc_line_num": 13, "premise_source_doc_sentence": "Swift was the sole writer of her 2010 album , Speak Now ."}
{"label_logits": [0.5567010641098022, -4.421988010406494, 2.1554160118103027], "label_probs": [0.16796687245368958, 0.0011561295250430703, 0.8308770060539246], "claim": "Taylor Swift is an American singer-songwriter.", "premise_source_doc_id": "Taylor_Swift", "premise_source_doc_line_num": 14, "premise_source_doc_sentence": "It debuted at number one in the United States and the single `` Mean '' won two Grammy Awards ."}
{"label_logits": [-1.3822497129440308, -3.792386293411255, 2.7827951908111572], "label_probs": [0.015270587056875229, 0.0013713447842746973, 0.9833580851554871], "claim": "Taylor Swift is an American singer-songwriter.", "premise_source_doc_id": "Taylor_Swift", "premise_source_doc_line_num": 15, "premise_source_doc_sentence": "Her fourth album , Red  (  2012  )  , yielded the successful singles `` We Are Never Ever Getting Back Together '' and `` I Knew You Were Trouble '' ."}
{"label_logits": [1.144220232963562, -4.710073947906494, 2.4132657051086426], "label_probs": [0.21928273141384125, 0.0006288061267696321, 0.780088484287262], "claim": "Taylor Swift is an American singer-songwriter.", "premise_source_doc_id": "Taylor_Swift", "premise_source_doc_line_num": 16, "premise_source_doc_sentence": "With her fifth album , the pop-focused 1989  (  2014  )  , she became the first act to have three albums sell a million copies within one week in the United States ."}
{"label_logits": [-1.8059698343276978, -2.081434726715088, 1.8468352556228638], "label_probs": [0.024788087233901024, 0.018819589167833328, 0.9563923478126526], "claim": "Taylor Swift is an American singer-songwriter.", "premise_source_doc_id": "Taylor_Swift", "premise_source_doc_line_num": 17, "premise_source_doc_sentence": "Its singles `` Shake It Off '' , `` Blank Space '' , and `` Bad Blood '' reached number one in the US , Australia , and Canada ."}
{"label_logits": [-0.2599266767501831, -3.3079121112823486, 2.237034559249878], "label_probs": [0.07579786330461502, 0.003596944035962224, 0.9206051826477051], "claim": "Taylor Swift is an American singer-songwriter.", "premise_source_doc_id": "Taylor_Swift", "premise_source_doc_line_num": 18, "premise_source_doc_sentence": "The album received three Grammy Awards , and Swift became the first woman and fifth act overall to win Album of the Year twice ."}
{"label_logits": [-3.2043039798736572, -1.5401275157928467, 2.921691656112671], "label_probs": [0.0021557232830673456, 0.011385070160031319, 0.9864591956138611], "claim": "Taylor Swift is an American singer-songwriter.", "premise_source_doc_id": "Taylor_Swift", "premise_source_doc_line_num": 19, "premise_source_doc_sentence": "The 2015 eponymous concert tour for 1989 became one of highest-grossing of the decade ."}
{"label_logits": [0.9566577672958374, -2.2870588302612305, 0.513962984085083], "label_probs": [0.5947701334953308, 0.023207100108265877, 0.38202276825904846], "claim": "Taylor Swift is an American singer-songwriter.", "premise_source_doc_id": "Taylor_Swift", "premise_source_doc_line_num": 22, "premise_source_doc_sentence": "As a songwriter , Swift has received awards from the Nashville Songwriters Association and the Songwriters Hall of Fame ."}
{"label_logits": [-1.971524953842163, -3.714794158935547, 3.543715238571167], "label_probs": [0.004006015602499247, 0.0007008423563092947, 0.995293140411377], "claim": "Taylor Swift is an American singer-songwriter.", "premise_source_doc_id": "Taylor_Swift", "premise_source_doc_line_num": 23, "premise_source_doc_sentence": "She is also the recipient of ten Grammy Awards , five Guinness World Records , one Emmy Award , 21 Billboard Music Awards , 11 Country Music Association Awards , eight Academy of Country Music Awards , and one Brit Award ."}
{"label_logits": [0.1611441671848297, -3.4933362007141113, 1.9457474946975708], "label_probs": [0.14320304989814758, 0.003705370705574751, 0.8530915975570679], "claim": "Taylor Swift is an American singer-songwriter.", "premise_source_doc_id": "Taylor_Swift", "premise_source_doc_line_num": 24, "premise_source_doc_sentence": "Swift is one of the best-selling artists of all time , having sold more than 40 million albums -- including 27.1 million in the US -- and 130 million single downloads ."}
{"label_logits": [0.16317224502563477, -4.658010005950928, 3.613736391067505], "label_probs": [0.030744420364499092, 0.0002477155940141529, 0.9690078496932983], "claim": "Taylor Swift is an American singer-songwriter.", "premise_source_doc_id": "Taylor_Swift", "premise_source_doc_line_num": 25, "premise_source_doc_sentence": "She has appeared in Time 100 most influential people in the world  (  2010 and 2015  )  , Forbes top-earning women in music  (  2011 -- 2015  )  , Forbes 100 most powerful women  (  2015  )  , and Forbes Celebrity 100  (  2016  )  ."}
{"label_logits": [-1.926184892654419, -4.421051502227783, 3.5151398181915283], "label_probs": [0.004313502460718155, 0.00035589601611718535, 0.9953305721282959], "claim": "Taylor Swift is an American singer-songwriter.", "premise_source_doc_id": "Taylor_Swift", "premise_source_doc_line_num": 26, "premise_source_doc_sentence": "She was the youngest woman to be included in the third of these and ranked first in Celebrity 100 ."}
{"label_logits": [3.800279378890991, -1.742641568183899, -2.7661144733428955], "label_probs": [0.9947062134742737, 0.0038943481631577015, 0.0013994139153510332], "claim": "Taylor Swift is an American singer-songwriter.", "premise_source_doc_id": "Taylor_Swift_-LRB-album-RRB-", "premise_source_doc_line_num": 0, "premise_source_doc_sentence": "Taylor Swift is the debut studio album by American singer-songwriter Taylor Swift , released on October 24 , 2006 , by Big Machine Records ."}
{"label_logits": [3.5112321376800537, -4.95671272277832, -0.15591295063495636], "label_probs": [0.974887490272522, 0.0002048201422439888, 0.024907702580094337], "claim": "Taylor Swift is an American singer-songwriter.", "premise_source_doc_id": "Taylor_Swift_discography", "premise_source_doc_line_num": 0, "premise_source_doc_sentence": "American singer-songwriter Taylor Swift 's career began with a record deal with Big Machine Records in 2005 and the release of her eponymous debut album the following year ."}
{"label_logits": [3.812830924987793, -4.657891750335693, -0.47882241010665894], "label_probs": [0.9862985610961914, 0.00020664290059357882, 0.013494820334017277], "claim": "Taylor Swift is an American singer-songwriter.", "premise_source_doc_id": "Taylor_Swift_videography", "premise_source_doc_line_num": 0, "premise_source_doc_sentence": "American singer-songwriter Taylor Swift has released four video albums and has appeared in thirty-eight music videos , five films and three television shows ."}
{"label_logits": [2.732755184173584, -1.479560375213623, -2.4489853382110596], "label_probs": [0.9799787998199463, 0.014515476301312447, 0.005505734588950872], "claim": "Taylor Swift is an American singer-songwriter.", "premise_source_doc_id": "Our_Song_-LRB-Taylor_Swift_song-RRB-", "premise_source_doc_line_num": 0, "premise_source_doc_sentence": "`` Our Song '' is a country song performed by American singer-songwriter Taylor Swift ."}
{"label_logits": [1.5253950357437134, -1.8967726230621338, -0.17788691818714142], "label_probs": [0.8232305645942688, 0.026871560141444206, 0.14989788830280304], "claim": "Taylor Swift is an American singer-songwriter.", "premise_source_doc_id": "The_Taylor_Swift_Holiday_Collection", "premise_source_doc_line_num": 0, "premise_source_doc_sentence": "The Taylor Swift Holiday Collection , originally titled Sounds of the Season : The Taylor Swift Holiday Collection , is a Christmas EP by American singer Taylor Swift ."}
