{"label_logits": [-2.9753382205963135, -2.0813686847686768, 2.636190891265869], "label_probs": [0.0036100156139582396, 0.008825821802020073, 0.9875641465187073], "claim": "Maisie Williams appeared in Game of Thrones.", "premise_source_doc_id": "Maisie_Williams", "premise_source_doc_line_num": 0, "premise_source_doc_sentence": "Margaret Constance `` Maisie '' Williams  (  born 15 April 1997  )  is an English actress ."}
{"label_logits": [1.5186454057693481, -2.493624448776245, -0.3917441964149475], "label_probs": [0.8575483560562134, 0.015515005216002464, 0.12693661451339722], "claim": "Maisie Williams appeared in Game of Thrones.", "premise_source_doc_id": "Maisie_Williams", "premise_source_doc_line_num": 1, "premise_source_doc_sentence": "She made her professional acting debut as Arya Stark in the HBO fantasy television series Game of Thrones in 2011 , for which she won the EWwy Award for Best Supporting Actress in a Drama , the Portal Award for Best Supporting Actress -- Television and Best Young Actor , and the Saturn Award for Best Performance by a Younger Actor ."}
{"label_logits": [-0.41468629240989685, -2.9759695529937744, 1.475736379623413], "label_probs": [0.12988071143627167, 0.01002751849591732, 0.8600917458534241], "claim": "Maisie Williams appeared in Game of Thrones.", "premise_source_doc_id": "Maisie_Williams", "premise_source_doc_line_num": 2, "premise_source_doc_sentence": "In 2016 , she was nominated for a Primetime Emmy Award for Outstanding Supporting Actress in a Drama Series ."}
{"label_logits": [0.07407175749540329, -2.0096209049224854, 0.08522777259349823], "label_probs": [0.4682331383228302, 0.058280859142541885, 0.4734860062599182], "claim": "Maisie Williams appeared in Game of Thrones.", "premise_source_doc_id": "Maisie_Williams", "premise_source_doc_line_num": 5, "premise_source_doc_sentence": "Williams has also had a recurring role in Doctor Who as Ashildr in 2015 ."}
{"label_logits": [0.1930544674396515, -2.872781276702881, 0.824851393699646], "label_probs": [0.3415764272212982, 0.015922537073493004, 0.6425009965896606], "claim": "Maisie Williams appeared in Game of Thrones.", "premise_source_doc_id": "Maisie_Williams", "premise_source_doc_line_num": 6, "premise_source_doc_sentence": "In addition to television , she made her feature film debut in the mystery The Falling  (  2014  )  , for which she won the London Film Critics ' Circle Award for Young Performer of the Year ."}
{"label_logits": [1.4345284700393677, -2.7566628456115723, -0.5396047830581665], "label_probs": [0.866543710231781, 0.013109292834997177, 0.12034700810909271], "claim": "Maisie Williams appeared in Game of Thrones.", "premise_source_doc_id": "Arya_Stark", "premise_source_doc_line_num": 9, "premise_source_doc_sentence": "Arya is portrayed by Maisie Williams on the HBO series Game of Thrones ."}
{"label_logits": [0.7341276407241821, -2.935943126678467, 0.531600832939148], "label_probs": [0.5428471565246582, 0.013828852213919163, 0.4433240294456482], "claim": "Maisie Williams appeared in Game of Thrones.", "premise_source_doc_id": "No_One_-LRB-Game_of_Thrones-RRB-", "premise_source_doc_line_num": 14, "premise_source_doc_sentence": "The episode was Maisie Williams ' and Peter Dinklage 's selection for the 68th Primetime Emmy Awards to support their nominations ."}
{"label_logits": [1.5708714723587036, -2.2815825939178467, -1.3058490753173828], "label_probs": [0.9280340075492859, 0.019699912518262863, 0.05226609855890274], "claim": "Maisie Williams appeared in Game of Thrones.", "premise_source_doc_id": "Game_of_Thrones", "premise_source_doc_line_num": 17, "premise_source_doc_sentence": "Lena Headey , Emilia Clarke , Kit Harington , Maisie Williams , Diana Rigg , and Max von Sydow have also received Primetime Emmy Award nominations for their performances in the series ."}
{"label_logits": [-2.782801866531372, -1.6469885110855103, 2.1906814575195312], "label_probs": [0.0067275227047502995, 0.020947519689798355, 0.9723249673843384], "claim": "Maisie Williams appeared in Game of Thrones.", "premise_source_doc_id": "Maisie_-LRB-given_name-RRB-", "premise_source_doc_line_num": 10, "premise_source_doc_sentence": "Maisie Williams  (  born 1997  )  , British actress"}
{"label_logits": [1.6026371717453003, -2.292315721511841, -1.4586282968521118], "label_probs": [0.9370554089546204, 0.019063768908381462, 0.043880801647901535], "claim": "Maisie Williams appeared in Game of Thrones.", "premise_source_doc_id": "List_of_awards_and_nominations_received_by_Game_of_Thrones", "premise_source_doc_line_num": 13, "premise_source_doc_sentence": "In addition , cast members Emilia Clarke , Lena Headey , Kit Harington , Maisie Williams , Diana Rigg , and Max von Sydow received Emmy nominations for their performances in the series ."}
