{"label_logits": [-4.165700435638428, -3.1833577156066895, 3.558915853500366], "label_probs": [0.00044110105955041945, 0.0011780511122196913, 0.9983808398246765], "claim": "Alec Sokolow produced the fantasy film Gnomes and Trolls: The Secret Chamber.", "premise_source_doc_id": "Alec_Sokolow", "premise_source_doc_line_num": 0, "premise_source_doc_sentence": "Alec Sokolow is an American film writer who has worked on such projects as the movies Cheaper by the Dozen , Toy Story , Money Talks , and Garfield : The Movie ."}
{"label_logits": [-4.284097671508789, -3.824120283126831, 4.184019088745117], "label_probs": [0.00020994617079850286, 0.0003325626312289387, 0.9994574785232544], "claim": "Alec Sokolow produced the fantasy film Gnomes and Trolls: The Secret Chamber.", "premise_source_doc_id": "Alec_Sokolow", "premise_source_doc_line_num": 1, "premise_source_doc_sentence": "He frequently works with Joel Cohen ."}
{"label_logits": [-2.635887861251831, -2.3286051750183105, 1.943435549736023], "label_probs": [0.010019221343100071, 0.013623385690152645, 0.9763574004173279], "claim": "Alec Sokolow produced the fantasy film Gnomes and Trolls: The Secret Chamber.", "premise_source_doc_id": "Alec_Sokolow", "premise_source_doc_line_num": 4, "premise_source_doc_sentence": "Along with Joss Whedon , Andrew Stanton , John Lasseter , Pete Docter , Joe Ranft , and Cohen , Sokolow was nominated in 1995 for the Academy Award for Best Writing  (  Original Screenplay  )  for his work on Toy Story ."}
{"label_logits": [1.0199414491653442, 0.4737202823162079, -2.7721354961395264], "label_probs": [0.6243433356285095, 0.3615785539150238, 0.014078142121434212], "claim": "Alec Sokolow produced the fantasy film Gnomes and Trolls: The Secret Chamber.", "premise_source_doc_id": "Alec_Sokolow", "premise_source_doc_line_num": 7, "premise_source_doc_sentence": "Beyond writing , Sokolow and Cohen jointly directed Monster Mash : The Movie and executive produced Gnomes and Trolls : The Secret Chamber  (  2008  )  ."}
{"label_logits": [0.0923200324177742, -0.728084921836853, -0.12479029595851898], "label_probs": [0.44541555643081665, 0.19609569013118744, 0.3584887683391571], "claim": "Alec Sokolow produced the fantasy film Gnomes and Trolls: The Secret Chamber.", "premise_source_doc_id": "Gnomes_and_Trolls-COLON-_The_Secret_Chamber", "premise_source_doc_line_num": 0, "premise_source_doc_sentence": "Gnomes and Trolls : The Secret Chamber is an 2008 Swedish animated children 's fantasy film directed by Robert Rhodin for the Stockholm-based studio White Shark ."}
{"label_logits": [1.0199414491653442, 0.4737202823162079, -2.7721354961395264], "label_probs": [0.6243433356285095, 0.3615785539150238, 0.014078142121434212], "claim": "Alec Sokolow produced the fantasy film Gnomes and Trolls: The Secret Chamber.", "premise_source_doc_id": "Alec_Sokolow", "premise_source_doc_line_num": 7, "premise_source_doc_sentence": "Beyond writing , Sokolow and Cohen jointly directed Monster Mash : The Movie and executive produced Gnomes and Trolls : The Secret Chamber  (  2008  )  ."}
{"label_logits": [1.0199414491653442, 0.4737202823162079, -2.7721354961395264], "label_probs": [0.6243433356285095, 0.3615785539150238, 0.014078142121434212], "claim": "Alec Sokolow produced the fantasy film Gnomes and Trolls: The Secret Chamber.", "premise_source_doc_id": "Joel_Cohen_-LRB-writer-RRB-", "premise_source_doc_line_num": 7, "premise_source_doc_sentence": "Beyond writing , Cohen and Sokolow jointly directed Monster Mash : The Movie and executive produced Gnomes and Trolls : The Secret Chamber  (  2008  )  ."}
{"label_logits": [-3.209655284881592, -2.514141082763672, 2.1869099140167236], "label_probs": [0.00447123171761632, 0.008963659405708313, 0.986565113067627], "claim": "Alec Sokolow produced the fantasy film Gnomes and Trolls: The Secret Chamber.", "premise_source_doc_id": "Gnomes_-LRB-book-RRB-", "premise_source_doc_line_num": 4, "premise_source_doc_sentence": "The 1980 film Gnomes , and the series David the Gnome and Wisdom of the Gnomes are based on this book ."}
{"label_logits": [-4.165700435638428, -3.1833577156066895, 3.558915853500366], "label_probs": [0.00044110105955041945, 0.0011780511122196913, 0.9983808398246765], "claim": "Alec Sokolow produced the fantasy film Gnomes and Trolls: The Secret Chamber.", "premise_source_doc_id": "Alec_Sokolow", "premise_source_doc_line_num": 0, "premise_source_doc_sentence": "Alec Sokolow is an American film writer who has worked on such projects as the movies Cheaper by the Dozen , Toy Story , Money Talks , and Garfield : The Movie ."}
