{"label_logits": [-7.549404621124268, 0.9066370129585266, 3.976423501968384], "label_probs": [9.433691047888715e-06, 0.04437045753002167, 0.9556201100349426], "claim": "The World Senior Chess Championship was destroyed by the World Chess Federation.", "premise_source_doc_id": "World_Fitness_Federation", "premise_source_doc_line_num": 0, "premise_source_doc_sentence": "The World Fitness Federation or WFF , is an international bodybuilding organisation formed in 1968 ."}
{"label_logits": [-7.260172367095947, 0.7897928357124329, 3.8720996379852295], "label_probs": [1.3990683328302111e-05, 0.04384239390492439, 0.9561436176300049], "claim": "The World Senior Chess Championship was destroyed by the World Chess Federation.", "premise_source_doc_id": "World_Fitness_Federation", "premise_source_doc_line_num": 1, "premise_source_doc_sentence": "The WFF promotes classic or athletic bodybuilding with a focus on the aesthetic quality of the physique as opposed to just muscularity ."}
{"label_logits": [0.9954158067703247, 4.215871334075928, -6.578973770141602], "label_probs": [0.03840239718556404, 0.9615778923034668, 1.971707933989819e-05], "claim": "The World Senior Chess Championship was destroyed by the World Chess Federation.", "premise_source_doc_id": "Elena_Fatalibekova", "premise_source_doc_line_num": 22, "premise_source_doc_sentence": "Fatalibekova is three-time winner of the Women 's World Senior Chess Championship  (  2000 , 2001 , 2004  )  and two-time winner of the Women 's European Senior Chess Championship  (  2007 , 2008  )  ."}
{"label_logits": [0.8101229071617126, 3.506425380706787, -5.197668075561523], "label_probs": [0.06318207830190659, 0.9366625547409058, 0.00015539719606749713], "claim": "The World Senior Chess Championship was destroyed by the World Chess Federation.", "premise_source_doc_id": "World_Chess_Championship", "premise_source_doc_line_num": 13, "premise_source_doc_sentence": "Other separate events and titles are the Women 's World Chess Championship , the World Junior Chess Championship  (  for players under 20 years of age  )  , and the World Senior Chess Championship  (  for men above 60 years of age , and women above 50  )  ."}
{"label_logits": [0.7518777847290039, 3.192871332168579, -4.92575740814209], "label_probs": [0.08007772266864777, 0.919648289680481, 0.0002739972551353276], "claim": "The World Senior Chess Championship was destroyed by the World Chess Federation.", "premise_source_doc_id": "Hans-Joachim_Hecht", "premise_source_doc_line_num": 34, "premise_source_doc_sentence": "Most recently , he has been involved in the promotion of German junior chess club Furstenfeldbruck , but also participated at the 2005 World Senior Chess Championship at Lignano Sabbiadoro , where he made a respectable top ten finish from a field of one hundred and forty ."}
{"label_logits": [0.2861200273036957, 3.6815013885498047, -5.093860626220703], "label_probs": [0.03243526816368103, 0.9674152731895447, 0.00014945886505302042], "claim": "The World Senior Chess Championship was destroyed by the World Chess Federation.", "premise_source_doc_id": "Viktor_Korchnoi", "premise_source_doc_line_num": 13, "premise_source_doc_sentence": "In September 2006 , he won the World Senior Chess Championship ."}
{"label_logits": [-0.49721696972846985, 2.826286554336548, -3.444918394088745], "label_probs": [0.03471030294895172, 0.9634687900543213, 0.0018209076952189207], "claim": "The World Senior Chess Championship was destroyed by the World Chess Federation.", "premise_source_doc_id": "World_Chess_Championship", "premise_source_doc_line_num": 5, "premise_source_doc_sentence": "From 1948 to 1993 , the championship was administered by FIDE , the World Chess Federation ."}
