{"label_logits": [-0.44671598076820374, -0.0382787249982357, -0.8291611075401306], "label_probs": [0.3138085603713989, 0.4721139669418335, 0.21407747268676758], "claim": "Fred Trump engaged in philanthropy.", "premise_source_doc_id": "Fred_Trump", "premise_source_doc_line_num": 0, "premise_source_doc_sentence": "Frederick Christ Trump  (  October 11 , 1905 -- June 25 , 1999  )  was an American real estate developer and philanthropist , primarily in New York City , and father of Donald Trump , the 45th President of the United States , and Maryanne Trump Barry , a United States Court of Appeals judge ."}
