{"label_logits": [-2.9427502155303955, 0.7953912019729614, 1.1482292413711548], "label_probs": [0.009725898504257202, 0.4086805284023285, 0.5815935134887695], "claim": "Susan Sarandon debuted in a movie by Gore Vidal.", "premise_source_doc_id": "Live_from_Golgotha-COLON-_The_Gospel_According_to_Gore_Vidal", "premise_source_doc_line_num": 0, "premise_source_doc_sentence": "Live from Golgotha : The Gospel according to Gore Vidal is a novel by Gore Vidal , an irreverent spoof of the New Testament ."}
